__init__.py
glycoenz/main.cp39-win_amd64.pyd
glycoenz/plugins/enzyme.cp39-win_amd64.pyd
glycoenz/plugins/param.cp39-win_amd64.pyd
glycoenz/plugins/visual.cp39-win_amd64.pyd
glycogene-0.1.0.dist-info/LICENSE
glycogene-0.1.0.dist-info/METADATA
glycogene-0.1.0.dist-info/WHEEL
glycogene-0.1.0.dist-info/entry_points.txt
glycogene-0.1.0.dist-info/top_level.txt
glycogene-0.1.0.dist-info/RECORD
